iprangetoolkit/README.MD
iprangetoolkit/__init__.py
iprangetoolkit/requirements.txt
iprangetoolkit/thirdparty.json
iprangetoolkit-0.10.dist-info/LICENSE.rst
iprangetoolkit-0.10.dist-info/METADATA
iprangetoolkit-0.10.dist-info/WHEEL
iprangetoolkit-0.10.dist-info/top_level.txt
iprangetoolkit-0.10.dist-info/RECORD
