Metadata-Version: 2.1
Name: iprangetoolkit
Version: 0.10
Summary: The IP Range Toolkit is a versatile Python library for generating and working with IP address ranges.
Home-page: https://github.com/hansalemaos/iprangetoolkit
Author: Johannes Fischer
Author-email: aulasparticularesdealemaosp@gmail.com
License: MIT
Keywords: range,ip,regex
Classifier: Development Status :: 4 - Beta
Classifier: Programming Language :: Python :: 3 :: Only
Classifier: Programming Language :: Python :: 3.10
Classifier: Topic :: Software Development :: Libraries :: Python Modules
Classifier: Topic :: Utilities
License-File: LICENSE.rst
Requires-Dist: numexpr
Requires-Dist: numpy
Requires-Dist: pandas
Requires-Dist: regex
